{
    "PP-0001" : "Grey Glitch",
    "PP-0002" : "Red Glitch",
    "PP-0003" : "Cyan Glitch",
    "PP-0004" : "Tori",
    "PP-0005" : "Quinn",
    "PP-0006" : "Enzo",
    "PP-0007" : "Iris",
    "PP-0008" : "Nova",
    "PP-0009" : "Klein",
    "PP-0010" : "Lumi",
    "PP-0011" : "Aven",
    "PP-0012" : "Stella",
    "PP-0013" : "Luna",
    "PP-0014" : "Bloom",
    "PP-0015" : "Dream",
    "PP-0016" : "Aqua",
    "PP-0017" : "Clay",
    "PP-0018" : "Myst",
    "PP-0019" : "Moss",
    "PP-0020" : "Breeze",
    "PP-0021" : "Echo",
    "PP-0022" : "Lava Claw",
    "PP-0023" : "Shadow Claw",
    "PP-0024" : "Scarlet Claw",
    "PP-0025" : "Blue Checkerboard",
    "PP-0026" : "BW Checkerboard",
    "PP-0027" : "Orange Checkerboard",
    "PP-0028" : "Bourbon",
    "PP-0029" : "Sherry",
    "PP-0030" : "Gin",
    "PP-0031" : "Mocha",
    "PP-0032" : "Matcha",
    "PP-0033" : "Honey",
    "PP-0034" : "Coral",
    "PP-0035" : "Amber",
    "PP-0036" : "Ash",
    "PP-0037" : "Lemon",
    "PP-0038" : "Cool Blue",
    "PP-0039" : "Lime",
    "PP-0040" : "Matrix Green",
    "PP-0041" : "Matrix Blue",
    "PP-0042" : "Matrix Red",
    "PP-0043" : "Leo",
    "PP-0044" : "Milo",
    "PP-0045" : "Luca",
    "PP-0046" : "Finch",
    "PP-0047" : "Otto",
    "PP-0048" : "Ruby",
    "PP-0049" : "Cheddar Cheese",
    "PP-0050" : "Berry Cheese",
    "PP-0051" : "Grape Cheese",
    "PP-0052" : "Fiery Cheese",
    "PP-0053" : "Herb Cheese",
    "PP-0054" : "Icy Blue Cheese",
    "PP-0055" : "Neon Pink",
    "PP-0056" : "Neon Blue",
    "PP-0057" : "Neon Yellow",
    "PP-0058" : "Neon Mint",
    "PP-0059" : "Neon Red",
    "PP-0060" : "Neon White",
    "PP-0061" : "Solid Blue",
    "PP-0062" : "Solid Grey",
    "PP-0063" : "Solid Green",
    "PP-0064" : "Amethyst Glow",
    "PP-0065" : "Ruby Glow",
    "PP-0066" : "Golden Glow",
    "PP-0067" : "Aqua Bubble",
    "PP-0068" : "Lime Bubble",
    "PP-0069" : "Violet Bubble",
    "PP-0070" : "Summer Ring",
    "PP-0071" : "Spring Ring",
    "PP-0072" : "Autumn Ring",
    "PP-0073" : "Data Desert",
    "PP-0074" : "Digital Tide",
    "PP-0075" : "Ghost Cache",
    "PP-0076" : "Taylor",
    "PP-0077" : "Dylan",
    "PP-0078" : "Sam",
    "PP-0079" : "Sage",
    "PP-0080" : "Elliot",
    "PP-0081" : "Theo",
    "PP-0082" : "Minty Pulse",
    "PP-0083" : "Cotton Pulse",
    "PP-0084" : "Peachy Pulse",
    "PP-0085" : "Jade Core",
    "PP-0086" : "Cyan Core",
    "PP-0087" : "Amber Core",
    "PP-0088" : "Frost Zone",
    "PP-0089" : "Crimson Zone",
    "PP-0090" : "Violet Zone",
    "PP-0091" : "Spring Melody",
    "PP-0092" : "Frost Melody",
    "PP-0093" : "Summer Melody",
    "PP-0094" : "Cora",
    "PP-0095" : "Viola",
    "PP-0096" : "Selene",
    "PP-0097" : "Amber Field",
    "PP-0098" : "Red Earth",
    "PP-0099" : "Jade Grove"
}
